bin/__init__.py
bin/rouge_cmd.py
rouge/__init__.py
rouge/rouge.py
rouge/rouge_score.py
rouge/utils.py
rouge-1.0.0.dist-info/LICENSE
rouge-1.0.0.dist-info/METADATA
rouge-1.0.0.dist-info/WHEEL
rouge-1.0.0.dist-info/entry_points.txt
rouge-1.0.0.dist-info/top_level.txt
rouge-1.0.0.dist-info/RECORD
