Metadata-Version: 2.1
Name: rouge
Version: 1.0.0
Summary: Full Python ROUGE Score Implementation (not a wrapper)
Home-page: http://github.com/pltrdy/rouge
Author: pltrdy
Author-email: pltrdy@gmail.com
License: LICENCE.txt
Download-URL: https://github.com/pltrdy/rouge/archive/1.0.0.tar.gz
Keywords: NL,CL,natural language processing,computational linguistics,summarization
Platform: UNKNOWN
Classifier: Intended Audience :: Science/Research
Classifier: Programming Language :: Python :: 3
Classifier: Topic :: Text Processing :: Linguistic
